gnssrtc/__init__.py
gnssrtc/epoch.py
gnssrtc/gps.py
gnssrtc/nmea.py
gnssrtc/py.typed
gnssrtc/server.py
gnssrtc/system.py
gnssrtc/zda.py
gnssrtc-0.4.0.dist-info/METADATA
gnssrtc-0.4.0.dist-info/WHEEL
gnssrtc-0.4.0.dist-info/licenses/LICENSE
gnssrtc-0.4.0.dist-info/RECORD
