Metadata-Version: 2.4
Name: gnssrtc
Version: 0.4.0
Summary: Modern, type-safe, zero-dependency python library for controlling GNSS RTC for the Raspberry Pi
Project-URL: Source, https://github.com/michealroberts/gnssrtc
Project-URL: Issues, https://github.com/michealroberts/gnssrtc/issues
Project-URL: PullRequests, https://github.com/michealroberts/gnssrtc/pulls
Project-URL: Discussions, https://github.com/michealroberts/gnssrtc/discussions
Author-email: michealroberts <michael@observerly.com>
Maintainer-email: Michael Roberts <michael@observerly.com>
License: MIT License
License-File: LICENSE
Keywords: gnss,gps,raspberry-pi,real-time-controller
Classifier: Development Status :: 3 - Alpha
Classifier: Intended Audience :: Developers
Classifier: License :: OSI Approved :: MIT License
Classifier: Programming Language :: Python :: 3.13
Requires-Python: >=3.13
Requires-Dist: gpiozero>=2.0.1
Requires-Dist: ntps>=0.2.0
Requires-Dist: pyserial>=3.5
Requires-Dist: rich>=14.0.0
